outerop/__init__.py
outerop-0.2.2.dist-info/METADATA
outerop-0.2.2.dist-info/WHEEL
outerop-0.2.2.dist-info/RECORD
