Metadata-Version: 2.1
Name: outerop
Version: 0.2.2
Summary: 
Author: Stephen Byrne
Author-email: 39441007+stephenbyrne99@users.noreply.github.com
Requires-Python: >=3.9,<4.0
Classifier: Programming Language :: Python :: 3
Classifier: Programming Language :: Python :: 3.9
Classifier: Programming Language :: Python :: 3.10
Classifier: Programming Language :: Python :: 3.11
Classifier: Programming Language :: Python :: 3.12
Requires-Dist: anthropic (>=0.21.0)
Requires-Dist: mistralai (>=0.1.0)
Requires-Dist: openai (>=1.14.0)
